<?xml version="1.0" encoding="UTF-8"?>
<items>
<profile type="contenttype">
    <title type="field">Государственный Академический Русский Народный Хор им. Пятницкого М.Е.</title>
    <field_location type="field">
        <latitude>55.768897</latitude>
        <longitude>37.596354</longitude>
    </field_location>
    <taxonomy type="taxonomy">
        <term take_parents="0" vid="6">Хоры и хоровые студии</term>
    </taxonomy>
    <field_goods type="field">
        <value></value>
    </field_goods>
    <field_address type="field">
        <value>Москва, ул. Тверская, 31</value>
    </field_address>
    <field_hours type="field">
         <value></value>
    </field_hours>
    <field_phone type="field">
        <value>+7 (495) 699-69-25</value>
    </field_phone>
    <field_email type="field">
        <value></value>
    </field_email>
</profile>
<profile type="contenttype">
    <title type="field">Государственный Академический Русский Хор им. Свешникова А.В.</title>
    <field_location type="field">
        <latitude>55.769226</latitude>
        <longitude>37.663602</longitude>
    </field_location>
    <taxonomy type="taxonomy">
        <term take_parents="0" vid="6">Хоры и хоровые студии</term>
    </taxonomy>
    <field_goods type="field">
        <value></value>
    </field_goods>
    <field_address type="field">
        <value>Москва, ул. Басманная Нов., 22</value>
    </field_address>
    <field_hours type="field">
         <value></value>
    </field_hours>
    <field_phone type="field">
        <value>+7 (499) 267-77-91</value>
    </field_phone>
    <field_phone type="field">
        <value>+7 (499) 267-97-32</value>
    </field_phone>
    <field_email type="field">
        <value></value>
    </field_email>
</profile>
<profile type="contenttype">
    <title type="field">Музыкально-Хоровая Студия Клуба Современник</title>
    <field_location type="field">
        <latitude>55.811831</latitude>
        <longitude>37.404591</longitude>
    </field_location>
    <taxonomy type="taxonomy">
        <term take_parents="0" vid="6">Хоры и хоровые студии</term>
    </taxonomy>
    <field_goods type="field">
        <value></value>
    </field_goods>
    <field_address type="field">
        <value>Москва, ул. Маршала Катукова, 9, корп.3</value>
    </field_address>
    <field_hours type="field">
         <value></value>
    </field_hours>
    <field_phone type="field">
        <value>+7 (495) 757-92-21</value>
    </field_phone>
    <field_email type="field">
        <value></value>
    </field_email>
</profile>
<profile type="contenttype">
    <title type="field">Московский Мужской Камерный Хор Под Управлением Валерия Рыбина</title>
    <field_location type="field">
        <latitude>55.784005</latitude>
        <longitude>37.704700</longitude>
    </field_location>
    <taxonomy type="taxonomy">
        <term take_parents="0" vid="6">Хоры и хоровые студии</term>
    </taxonomy>
    <field_goods type="field">
        <value></value>
    </field_goods>
    <field_address type="field">
        <value>Москва, пл. Журавлева, 1, стр. 1</value>
    </field_address>
    <field_hours type="field">
         <value></value>
    </field_hours>
    <field_phone type="field">
        <value>+7 (495) 963-54-18</value>
    </field_phone>
    <field_phone type="field">
        <value>+7 (495) 963-54-11</value>
    </field_phone>
    <field_email type="field">
        <value></value>
    </field_email>
</profile>
<profile type="contenttype">
    <title type="field">Академический Хор Под Управлением Кожевникова А.Д.</title>
    <field_location type="field">
        <latitude>55.633795</latitude>
        <longitude>37.617132</longitude>
    </field_location>
    <taxonomy type="taxonomy">
        <term take_parents="0" vid="6">Хоры и хоровые студии</term>
    </taxonomy>
    <field_goods type="field">
        <value></value>
    </field_goods>
    <field_address type="field">
        <value>Москва, Варшавское ш., 116</value>
    </field_address>
    <field_hours type="field">
         <value></value>
    </field_hours>
    <field_phone type="field">
        <value>+7 (495) 318-58-69</value>
    </field_phone>
    <field_email type="field">
        <value></value>
    </field_email>
</profile>
<profile type="contenttype">
    <title type="field">Московский Армянский Камерный Хор</title>
    <field_location type="field">
        <latitude>55.760677</latitude>
        <longitude>37.633913</longitude>
    </field_location>
    <taxonomy type="taxonomy">
        <term take_parents="0" vid="6">Хоры и хоровые студии</term>
    </taxonomy>
    <field_goods type="field">
        <value></value>
    </field_goods>
    <field_address type="field">
        <value>Москва, Армянский пер., 2</value>
    </field_address>
    <field_hours type="field">
         <value></value>
    </field_hours>
    <field_phone type="field">
        <value>+7 (495) 615-78-64</value>
    </field_phone>
    <field_email type="field">
        <value></value>
    </field_email>
</profile>
<profile type="contenttype">
    <title type="field">Детский Хор Маковец</title>
    <field_location type="field">
        <latitude>55.877602</latitude>
        <longitude>37.618273</longitude>
    </field_location>
    <taxonomy type="taxonomy">
        <term take_parents="0" vid="6">Хоры и хоровые студии</term>
    </taxonomy>
    <field_goods type="field">
        <value></value>
    </field_goods>
    <field_address type="field">
        <value>Москва, просп. Ясный, 21</value>
    </field_address>
    <field_hours type="field">
         <value></value>
    </field_hours>
    <field_phone type="field">
        <value>+7 (495) 477-13-13</value>
    </field_phone>
    <field_email type="field">
        <value></value>
    </field_email>
</profile>
<profile type="contenttype">
    <title type="field">Академический Хор Русской Песни Под Управлением Кутузова Н. в</title>
    <field_location type="field">
        <latitude>55.741764</latitude>
        <longitude>37.630769</longitude>
    </field_location>
    <taxonomy type="taxonomy">
        <term take_parents="0" vid="6">Хоры и хоровые студии</term>
    </taxonomy>
    <field_goods type="field">
        <value></value>
    </field_goods>
    <field_address type="field">
        <value>Москва, ул. Пятницкая, 25</value>
    </field_address>
    <field_hours type="field">
         <value></value>
    </field_hours>
    <field_phone type="field">
        <value>+7 (495) 633-54-01</value>
    </field_phone>
    <field_email type="field">
        <value></value>
    </field_email>
</profile>
<profile type="contenttype">
    <title type="field">Московская Хоровая Капелла Мальчиков</title>
    <field_location type="field">
        <latitude>55.765417</latitude>
        <longitude>37.601151</longitude>
    </field_location>
    <taxonomy type="taxonomy">
        <term take_parents="0" vid="6">Хоры и хоровые студии</term>
    </taxonomy>
    <field_goods type="field">
        <value></value>
    </field_goods>
    <field_address type="field">
        <value>Москва, Палашевский М. пер., 3</value>
    </field_address>
    <field_hours type="field">
         <value></value>
    </field_hours>
    <field_phone type="field">
        <value>+7 (495) 694-10-71</value>
    </field_phone>
    <field_email type="field">
        <value></value>
    </field_email>
</profile>
<profile type="contenttype">
    <title type="field">Государственная Академическая Хоровая Капелла России им. Юрлова А.А.</title>
    <field_location type="field">
        <latitude>55.799188</latitude>
        <longitude>37.622890</longitude>
    </field_location>
    <taxonomy type="taxonomy">
        <term take_parents="0" vid="6">Хоры и хоровые студии</term>
    </taxonomy>
    <field_goods type="field">
        <value></value>
    </field_goods>
    <field_address type="field">
        <value>Москва, просп. Марьиной Рощи 3-й, 40, стр. 2</value>
    </field_address>
    <field_hours type="field">
         <value></value>
    </field_hours>
    <field_phone type="field">
        <value>+7 (495) 689-05-55</value>
    </field_phone>
    <field_email type="field">
        <value></value>
    </field_email>
</profile>
<profile type="contenttype">
    <title type="field">Центр Эстрадно-Джазового Музыкального Образования и Творчества</title>
    <field_location type="field">
        <latitude>55.733548</latitude>
        <longitude>37.655562</longitude>
    </field_location>
    <taxonomy type="taxonomy">
        <term take_parents="0" vid="6">Хоры и хоровые студии</term>
    </taxonomy>
    <field_goods type="field">
        <value></value>
    </field_goods>
    <field_address type="field">
        <value>Москва, Новоспасский пер., 3, корп.3</value>
    </field_address>
    <field_hours type="field">
         <value></value>
    </field_hours>
    <field_phone type="field">
        <value>+7 (495) 912-45-84</value>
    </field_phone>
    <field_email type="field">
        <value></value>
    </field_email>
</profile>
<profile type="contenttype">
    <title type="field">Московское Хоровое Училище им. А.В. Свешникова при Академии Хорового Искусства</title>
    <field_location type="field">
        <latitude>55.856401</latitude>
        <longitude>37.483580</longitude>
    </field_location>
    <taxonomy type="taxonomy">
        <term take_parents="0" vid="6">Хоры и хоровые студии</term>
    </taxonomy>
    <field_goods type="field">
        <value></value>
    </field_goods>
    <field_address type="field">
        <value>Москва, ул. Фестивальная, 2</value>
    </field_address>
    <field_hours type="field">
         <value></value>
    </field_hours>
    <field_phone type="field">
        <value>+7 (495) 459-62-74</value>
    </field_phone>
    <field_phone type="field">
        <value>+7 (495) 457-06-41</value>
    </field_phone>
    <field_phone type="field">
        <value>+7 (495) 457-61-34</value>
    </field_phone>
    <field_phone type="field">
        <value>+7 (495) 459-69-75</value>
    </field_phone>
    <field_email type="field">
        <value></value>
    </field_email>
</profile>
</items>