<?xml version="1.0" encoding="UTF-8"?>
<items>
<profile type="contenttype">
    <title type="field">Имидж-лаборатория Лиса</title>
    <field_location type="field">
        <latitude>55.796516</latitude>
        <longitude>38.440393</longitude>
    </field_location>
    <taxonomy type="taxonomy">
        <term take_parents="0" vid="6">Визажисты, стилисты</term>
    </taxonomy>
    <field_goods type="field">
        <value></value>
    </field_goods>
    <field_address type="field">
        <value>Московская обл., Электросталь г., просп. Ленина, 25</value>
    </field_address>
    <field_hours type="field">
         <value></value>
    </field_hours>
    <field_phone type="field">
        <value>+7 (49657) 7-80-49</value>
    </field_phone>
    <field_email type="field">
        <value></value>
    </field_email>
</profile>
<profile type="contenttype">
    <title type="field">Лика</title>
    <field_location type="field">
        <latitude>56.735190</latitude>
        <longitude>37.159494</longitude>
    </field_location>
    <taxonomy type="taxonomy">
        <term take_parents="0" vid="6">Визажисты, стилисты</term>
    </taxonomy>
    <field_goods type="field">
        <value></value>
    </field_goods>
    <field_address type="field">
        <value>Московская обл., Дубна г., просп. Боголюбова, 19а</value>
    </field_address>
    <field_hours type="field">
         <value></value>
    </field_hours>
    <field_phone type="field">
        <value>+7 (49621) 2-01-75</value>
    </field_phone>
    <field_email type="field">
        <value></value>
    </field_email>
</profile>
<profile type="contenttype">
    <title type="field">Салон-красоты Екатерина</title>
    <field_location type="field">
        <latitude>55.57707</latitude>
        <longitude>38.234184</longitude>
    </field_location>
    <taxonomy type="taxonomy">
        <term take_parents="0" vid="6">Визажисты, стилисты</term>
    </taxonomy>
    <field_goods type="field">
        <value></value>
    </field_goods>
    <field_address type="field">
        <value>Московская обл., Раменское г., ул. Свободы, 4, стр. А, ТЦ Альянс</value>
    </field_address>
    <field_hours type="field">
         <value></value>
    </field_hours>
    <field_phone type="field">
        <value>+7 (495) 229-35-39</value>
    </field_phone>
    <field_phone type="field">
        <value>+7 (965) 286-02-06</value>
    </field_phone>
    <field_email type="field">
        <value></value>
    </field_email>
</profile>
</items>