<?xml version="1.0" encoding="UTF-8"?>
<items>
<profile type="contenttype">
    <title type="field">Подольский завод Строительных Материалов</title>
    <field_location type="field">
        <latitude>55.432699</latitude>
        <longitude>37.548869</longitude>
    </field_location>
    <taxonomy type="taxonomy">
        <term take_parents="0" vid="6">ЖБИ</term>
    </taxonomy>
    <field_goods type="field">
        <value></value>
    </field_goods>
    <field_address type="field">
        <value>Московская обл., Подольск г., Ремонтный пр-д, 6</value>
    </field_address>
    <field_hours type="field">
         <value></value>
    </field_hours>
    <field_phone type="field">
        <value>+7 (4967) 63-28-68</value>
    </field_phone>
    <field_email type="field">
        <value></value>
    </field_email>
</profile>
<profile type="contenttype">
    <title type="field">Компания КСК</title>
    <field_location type="field">
        <latitude>55.801050</latitude>
        <longitude>37.981695</longitude>
    </field_location>
    <taxonomy type="taxonomy">
        <term take_parents="0" vid="6">ЖБИ</term>
    </taxonomy>
    <field_goods type="field">
        <value></value>
    </field_goods>
    <field_address type="field">
        <value>Московская обл., Балашиха г., ш. Северное, вл. 2</value>
    </field_address>
    <field_hours type="field">
         <value></value>
    </field_hours>
    <field_phone type="field">
        <value>+7 (495) 545-56-17</value>
    </field_phone>
    <field_phone type="field">
        <value>+7 (495) 720-51-36</value>
    </field_phone>
    <field_email type="field">
        <value></value>
    </field_email>
</profile>
<profile type="contenttype">
    <title type="field">Часцовский завод Железобетонных Изделий при Спецстрое России ФГУП</title>
    <field_location type="field">
        <latitude>55.618618</latitude>
        <longitude>36.862386</longitude>
    </field_location>
    <taxonomy type="taxonomy">
        <term take_parents="0" vid="6">ЖБИ</term>
    </taxonomy>
    <field_goods type="field">
        <value></value>
    </field_goods>
    <field_address type="field">
        <value>Московская обл., Одинцовский р-н, Часцы пос.</value>
    </field_address>
    <field_hours type="field">
         <value></value>
    </field_hours>
    <field_phone type="field">
        <value>+7 (495) 992-59-38</value>
    </field_phone>
    <field_phone type="field">
        <value>+7 (495) 992-92-67</value>
    </field_phone>
    <field_phone type="field">
        <value>+7 (495) 992-49-08</value>
    </field_phone>
    <field_email type="field">
        <value></value>
    </field_email>
</profile>
<profile type="contenttype">
    <title type="field">Клинстройсервис</title>
    <field_location type="field">
        <latitude>56.350482</latitude>
        <longitude>36.702018</longitude>
    </field_location>
    <taxonomy type="taxonomy">
        <term take_parents="0" vid="6">ЖБИ</term>
    </taxonomy>
    <field_goods type="field">
        <value></value>
    </field_goods>
    <field_address type="field">
        <value>Московская обл., Клинский р-н, Клин г., ул. Терешковой, 48</value>
    </field_address>
    <field_hours type="field">
         <value></value>
    </field_hours>
    <field_phone type="field">
        <value>+7 (49624) 2-21-59</value>
    </field_phone>
    <field_email type="field">
        <value></value>
    </field_email>
</profile>
<profile type="contenttype">
    <title type="field">РФК Групп</title>
    <field_location type="field">
        <latitude>55.605932</latitude>
        <longitude>38.125174</longitude>
    </field_location>
    <taxonomy type="taxonomy">
        <term take_parents="0" vid="6">ЖБИ</term>
    </taxonomy>
    <field_goods type="field">
        <value></value>
    </field_goods>
    <field_address type="field">
        <value>Московская обл., Жуковский г., ул. Праволинейная, 33</value>
    </field_address>
    <field_hours type="field">
         <value></value>
    </field_hours>
    <field_phone type="field">
        <value>+7 (495) 556-02-49</value>
    </field_phone>
    <field_email type="field">
        <value></value>
    </field_email>
</profile>
<profile type="contenttype">
    <title type="field">Орехово-Зуевский комбинат Производственных Предприятий ДООО</title>
    <field_location type="field">
        <latitude>55.842509</latitude>
        <longitude>38.959979</longitude>
    </field_location>
    <taxonomy type="taxonomy">
        <term take_parents="0" vid="6">ЖБИ</term>
    </taxonomy>
    <field_goods type="field">
        <value></value>
    </field_goods>
    <field_address type="field">
        <value>Московская обл., Орехово-Зуевский р-н, Пригородный пос., 47</value>
    </field_address>
    <field_hours type="field">
         <value></value>
    </field_hours>
    <field_phone type="field">
        <value>+7 (4964) 23-43-49</value>
    </field_phone>
    <field_email type="field">
        <value></value>
    </field_email>
</profile>
<profile type="contenttype">
    <title type="field">Клинский завод Железобетонных Изделий</title>
    <field_location type="field">
        <latitude>56.354936</latitude>
        <longitude>36.699970</longitude>
    </field_location>
    <taxonomy type="taxonomy">
        <term take_parents="0" vid="6">ЖБИ</term>
    </taxonomy>
    <field_goods type="field">
        <value></value>
    </field_goods>
    <field_address type="field">
        <value>Московская обл., Клинский р-н, Клин г., ул. Терешковой, 21</value>
    </field_address>
    <field_hours type="field">
         <value></value>
    </field_hours>
    <field_phone type="field">
        <value>+7 (49624) 2-90-96</value>
    </field_phone>
    <field_phone type="field">
        <value>+7 (49624) 2-54-08</value>
    </field_phone>
    <field_email type="field">
        <value></value>
    </field_email>
</profile>
<profile type="contenttype">
    <title type="field">Железобетонных Изделий комбинат</title>
    <field_location type="field">
        <latitude>56.290260</latitude>
        <longitude>38.131139</longitude>
    </field_location>
    <taxonomy type="taxonomy">
        <term take_parents="0" vid="6">ЖБИ</term>
    </taxonomy>
    <field_goods type="field">
        <value></value>
    </field_goods>
    <field_address type="field">
        <value>Московская обл., Сергиево-Посадский р-н, Сергиев Посад, ш. Скобяное, 5</value>
    </field_address>
    <field_hours type="field">
         <value></value>
    </field_hours>
    <field_phone type="field">
        <value>+7 (495) 540-42-56</value>
    </field_phone>
    <field_phone type="field">
        <value>+7 (49654) 4-42-56</value>
    </field_phone>
    <field_email type="field">
        <value></value>
    </field_email>
</profile>
<profile type="contenttype">
    <title type="field">Твиком</title>
    <field_location type="field">
        <latitude>55.744252</latitude>
        <longitude>38.015903</longitude>
    </field_location>
    <taxonomy type="taxonomy">
        <term take_parents="0" vid="6">ЖБИ</term>
    </taxonomy>
    <field_goods type="field">
        <value></value>
    </field_goods>
    <field_address type="field">
        <value>Московская обл., Железнодорожный г.</value>
    </field_address>
    <field_hours type="field">
         <value></value>
    </field_hours>
    <field_phone type="field">
        <value>+7 (916) 609-27-25</value>
    </field_phone>
    <field_email type="field">
        <value></value>
    </field_email>
</profile>
<profile type="contenttype">
    <title type="field">Резонанс ПК</title>
    <field_location type="field">
        <latitude>55.545788</latitude>
        <longitude>37.072996</longitude>
    </field_location>
    <taxonomy type="taxonomy">
        <term take_parents="0" vid="6">ЖБИ</term>
    </taxonomy>
    <field_goods type="field">
        <value></value>
    </field_goods>
    <field_address type="field">
        <value>Московская обл., Наро-Фоминский р-н, Апрелевка г., ул. Ленина, 9</value>
    </field_address>
    <field_hours type="field">
         <value></value>
    </field_hours>
    <field_phone type="field">
        <value>+7 (49634) 1-49-07</value>
    </field_phone>
    <field_email type="field">
        <value></value>
    </field_email>
</profile>
<profile type="contenttype">
    <title type="field">Тест Инжиниринг</title>
    <field_location type="field">
        <latitude>55.680834</latitude>
        <longitude>37.266619</longitude>
    </field_location>
    <taxonomy type="taxonomy">
        <term take_parents="0" vid="6">ЖБИ</term>
    </taxonomy>
    <field_goods type="field">
        <value></value>
    </field_goods>
    <field_address type="field">
        <value>Московская обл., Одинцовский р-н, Одинцово г., ул. Маршала Жукова, 34</value>
    </field_address>
    <field_hours type="field">
         <value></value>
    </field_hours>
    <field_phone type="field">
        <value>+7 (985) 924-65-63</value>
    </field_phone>
    <field_email type="field">
        <value></value>
    </field_email>
</profile>
<profile type="contenttype">
    <title type="field">ПСП Стройматериалы</title>
    <field_location type="field">
        <latitude>55.629664</latitude>
        <longitude>37.842555</longitude>
    </field_location>
    <taxonomy type="taxonomy">
        <term take_parents="0" vid="6">ЖБИ</term>
    </taxonomy>
    <field_goods type="field">
        <value></value>
    </field_goods>
    <field_address type="field">
        <value>Московская обл., Люберецкий р-н, Дзержинский г., ул. Стройгородок, 5</value>
    </field_address>
    <field_hours type="field">
         <value></value>
    </field_hours>
    <field_phone type="field">
        <value>+7 (495) 551-55-11</value>
    </field_phone>
    <field_phone type="field">
        <value>+7 (495) 551-68-54</value>
    </field_phone>
    <field_email type="field">
        <value></value>
    </field_email>
</profile>
<profile type="contenttype">
    <title type="field">Домодедовский завод Железобетонных Изделий</title>
    <field_location type="field">
        <latitude>55.443592</latitude>
        <longitude>37.772385</longitude>
    </field_location>
    <taxonomy type="taxonomy">
        <term take_parents="0" vid="6">ЖБИ</term>
    </taxonomy>
    <field_goods type="field">
        <value></value>
    </field_goods>
    <field_address type="field">
        <value>Московская обл., Домодедово г., ул. Промышленная, 9</value>
    </field_address>
    <field_hours type="field">
         <value></value>
    </field_hours>
    <field_phone type="field">
        <value>+7 (495) 787-91-28</value>
    </field_phone>
    <field_email type="field">
        <value></value>
    </field_email>
</profile>
<profile type="contenttype">
    <title type="field">Полином</title>
    <field_location type="field">
        <latitude>55.612772</latitude>
        <longitude>38.144991</longitude>
    </field_location>
    <taxonomy type="taxonomy">
        <term take_parents="0" vid="6">ЖБИ</term>
    </taxonomy>
    <field_goods type="field">
        <value></value>
    </field_goods>
    <field_address type="field">
        <value>Московская обл., Раменский р-н, Бронницы г., ул. Льва Толстого, 23</value>
    </field_address>
    <field_hours type="field">
         <value></value>
    </field_hours>
    <field_phone type="field">
        <value>+7 (495) 660-12-41</value>
    </field_phone>
    <field_email type="field">
        <value></value>
    </field_email>
</profile>
<profile type="contenttype">
    <title type="field">Производственная Строительная Компания Стройсервис</title>
    <field_location type="field">
        <latitude>55.789699</latitude>
        <longitude>37.958869</longitude>
    </field_location>
    <taxonomy type="taxonomy">
        <term take_parents="0" vid="6">ЖБИ</term>
    </taxonomy>
    <field_goods type="field">
        <value></value>
    </field_goods>
    <field_address type="field">
        <value>Московская обл., Балашихинский р-н, Балашиха г., ул. Карбышева, 1</value>
    </field_address>
    <field_hours type="field">
         <value></value>
    </field_hours>
    <field_phone type="field">
        <value>+7 (495) 529-60-35</value>
    </field_phone>
    <field_email type="field">
        <value></value>
    </field_email>
</profile>
<profile type="contenttype">
    <title type="field">Центротрансжелезобетон филиал Силикатненский завод железобетонных конструкций г. Подольск</title>
    <field_location type="field">
        <latitude>55.480465</latitude>
        <longitude>37.572863</longitude>
    </field_location>
    <taxonomy type="taxonomy">
        <term take_parents="0" vid="6">ЖБИ</term>
    </taxonomy>
    <field_goods type="field">
        <value></value>
    </field_goods>
    <field_address type="field">
        <value>Московская обл., Подольский р-н, Подольск г., ул. Восьмого Марта, 2</value>
    </field_address>
    <field_hours type="field">
         <value></value>
    </field_hours>
    <field_phone type="field">
        <value>+7 (495) 941-90-48</value>
    </field_phone>
    <field_phone type="field">
        <value>+7 (4967) 65-02-03</value>
    </field_phone>
    <field_phone type="field">
        <value>+7 (4967) 65-00-07</value>
    </field_phone>
    <field_email type="field">
        <value></value>
    </field_email>
</profile>
<profile type="contenttype">
    <title type="field">Хотьковский завод Железобетонных Изделий г. Хотьково</title>
    <field_location type="field">
        <latitude>56.241529</latitude>
        <longitude>37.992637</longitude>
    </field_location>
    <taxonomy type="taxonomy">
        <term take_parents="0" vid="6">ЖБИ</term>
    </taxonomy>
    <field_goods type="field">
        <value></value>
    </field_goods>
    <field_address type="field">
        <value>Московская обл., Сергиево-Посадский р-н, Хотьково г., Художественный пр-д, 6</value>
    </field_address>
    <field_hours type="field">
         <value></value>
    </field_hours>
    <field_phone type="field">
        <value>+7 (496) 543-25-50</value>
    </field_phone>
    <field_email type="field">
        <value></value>
    </field_email>
</profile>
<profile type="contenttype">
    <title type="field">Комбинат Производственных Предприятий г. Наро-Фоминск</title>
    <field_location type="field">
        <latitude>55.372953</latitude>
        <longitude>36.714244</longitude>
    </field_location>
    <taxonomy type="taxonomy">
        <term take_parents="0" vid="6">ЖБИ</term>
    </taxonomy>
    <field_goods type="field">
        <value></value>
    </field_goods>
    <field_address type="field">
        <value>Московская обл., Наро-Фоминский р-н, Наро-Фоминск г., Тургеневский тупик, 1</value>
    </field_address>
    <field_hours type="field">
         <value></value>
    </field_hours>
    <field_phone type="field">
        <value>+7 (496) 343-64-71</value>
    </field_phone>
    <field_phone type="field">
        <value>+7 (496) 343-04-46</value>
    </field_phone>
    <field_phone type="field">
        <value>+7 (496) 343-66-05</value>
    </field_phone>
    <field_email type="field">
        <value></value>
    </field_email>
</profile>
<profile type="contenttype">
    <title type="field">УПТК Монолит</title>
    <field_location type="field">
        <latitude>55.629664</latitude>
        <longitude>37.842555</longitude>
    </field_location>
    <taxonomy type="taxonomy">
        <term take_parents="0" vid="6">ЖБИ</term>
    </taxonomy>
    <field_goods type="field">
        <value></value>
    </field_goods>
    <field_address type="field">
        <value>Московская обл., Люберецкий р-н, Дзержинский г., ул. Стройгородок, 5</value>
    </field_address>
    <field_hours type="field">
         <value></value>
    </field_hours>
    <field_phone type="field">
        <value>+7 (495) 644-65-26</value>
    </field_phone>
    <field_phone type="field">
        <value>+7 (495) 551-64-33</value>
    </field_phone>
    <field_email type="field">
        <value></value>
    </field_email>
</profile>
<profile type="contenttype">
    <title type="field">Арм-Строй г. Яхрома</title>
    <field_location type="field">
        <latitude>56.292463</latitude>
        <longitude>37.482547</longitude>
    </field_location>
    <taxonomy type="taxonomy">
        <term take_parents="0" vid="6">ЖБИ</term>
    </taxonomy>
    <field_goods type="field">
        <value></value>
    </field_goods>
    <field_address type="field">
        <value>Московская обл., Дмитровский р-н, Яхрома г., ул. Профессиональная, 4</value>
    </field_address>
    <field_hours type="field">
         <value></value>
    </field_hours>
    <field_phone type="field">
        <value>+7 (496) 224-23-66</value>
    </field_phone>
    <field_email type="field">
        <value></value>
    </field_email>
</profile>
<profile type="contenttype">
    <title type="field">Шатурский завод Железобетонных Изделий г. Шатура</title>
    <field_location type="field">
        <latitude>55.573648</latitude>
        <longitude>39.546633</longitude>
    </field_location>
    <taxonomy type="taxonomy">
        <term take_parents="0" vid="6">ЖБИ</term>
    </taxonomy>
    <field_goods type="field">
        <value></value>
    </field_goods>
    <field_address type="field">
        <value>Московская обл., Шатурский р-н, Шатура г., ул. Советская, 1а</value>
    </field_address>
    <field_hours type="field">
         <value></value>
    </field_hours>
    <field_phone type="field">
        <value>+7 (49645) 2-53-69</value>
    </field_phone>
    <field_phone type="field">
        <value>+7 (49645) 2-08-50</value>
    </field_phone>
    <field_phone type="field">
        <value>+7 (49645) 2-53-50</value>
    </field_phone>
    <field_phone type="field">
        <value>+7 (49645) 2-53-51</value>
    </field_phone>
    <field_email type="field">
        <value></value>
    </field_email>
</profile>
<profile type="contenttype">
    <title type="field">Предприниматель Смирнов А.В.</title>
    <field_location type="field">
        <latitude>55.842509</latitude>
        <longitude>38.959979</longitude>
    </field_location>
    <taxonomy type="taxonomy">
        <term take_parents="0" vid="6">ЖБИ</term>
    </taxonomy>
    <field_goods type="field">
        <value></value>
    </field_goods>
    <field_address type="field">
        <value>Московская обл., Орехово-Зуевский р-н, Пригородный пос., 1а</value>
    </field_address>
    <field_hours type="field">
         <value></value>
    </field_hours>
    <field_phone type="field">
        <value>+7 (496) 423-43-28</value>
    </field_phone>
    <field_phone type="field">
        <value>+7 (905) 531-23-19</value>
    </field_phone>
    <field_email type="field">
        <value></value>
    </field_email>
</profile>
<profile type="contenttype">
    <title type="field">Завод Железобетонных Конструкций и Строительных Деталей г. Коломна</title>
    <field_location type="field">
        <latitude>55.058116</latitude>
        <longitude>38.862062</longitude>
    </field_location>
    <taxonomy type="taxonomy">
        <term take_parents="0" vid="6">ЖБИ</term>
    </taxonomy>
    <field_goods type="field">
        <value></value>
    </field_goods>
    <field_address type="field">
        <value>Московская обл., Коломенский р-н, Коломна г., ул. Октябрьская, 107</value>
    </field_address>
    <field_hours type="field">
         <value></value>
    </field_hours>
    <field_phone type="field">
        <value>+7 (496) 615-19-21</value>
    </field_phone>
    <field_phone type="field">
        <value>+7 (496) 615-25-38</value>
    </field_phone>
    <field_phone type="field">
        <value>+7 (496) 615-21-99</value>
    </field_phone>
    <field_email type="field">
        <value></value>
    </field_email>
</profile>
<profile type="contenttype">
    <title type="field">Завод Железобетонных Изделий г. Черноголовка</title>
    <field_location type="field">
        <latitude>55.877955</latitude>
        <longitude>38.349331</longitude>
    </field_location>
    <taxonomy type="taxonomy">
        <term take_parents="0" vid="6">ЖБИ</term>
    </taxonomy>
    <field_goods type="field">
        <value></value>
    </field_goods>
    <field_address type="field">
        <value>Московская обл., Ногинский р-н, Черноголовка г.</value>
    </field_address>
    <field_hours type="field">
         <value></value>
    </field_hours>
    <field_phone type="field">
        <value>+7 (49652) 2-19-77</value>
    </field_phone>
    <field_phone type="field">
        <value>+7 (49652) 2-51-37</value>
    </field_phone>
    <field_email type="field">
        <value></value>
    </field_email>
</profile>
<profile type="contenttype">
    <title type="field">Стройнефтепродукт г. Озеры</title>
    <field_location type="field">
        <latitude>54.851283</latitude>
        <longitude>38.520730</longitude>
    </field_location>
    <taxonomy type="taxonomy">
        <term take_parents="0" vid="6">ЖБИ</term>
    </taxonomy>
    <field_goods type="field">
        <value></value>
    </field_goods>
    <field_address type="field">
        <value>Московская обл., Озерский р-н, Озеры г., ул. Ленина, 106</value>
    </field_address>
    <field_hours type="field">
         <value></value>
    </field_hours>
    <field_phone type="field">
        <value>+7 (49670) 2-10-52</value>
    </field_phone>
    <field_email type="field">
        <value></value>
    </field_email>
</profile>
<profile type="contenttype">
    <title type="field">Дзержинский завод ЖБИ</title>
    <field_location type="field">
        <latitude>55.629664</latitude>
        <longitude>37.842555</longitude>
    </field_location>
    <taxonomy type="taxonomy">
        <term take_parents="0" vid="6">ЖБИ</term>
    </taxonomy>
    <field_goods type="field">
        <value></value>
    </field_goods>
    <field_address type="field">
        <value>Московская обл., Дзержинский г., ул. Стройгородок, 5</value>
    </field_address>
    <field_hours type="field">
         <value></value>
    </field_hours>
    <field_phone type="field">
        <value>+7 (495) 551-68-54</value>
    </field_phone>
    <field_phone type="field">
        <value>+7 (495) 551-55-11</value>
    </field_phone>
    <field_email type="field">
        <value></value>
    </field_email>
</profile>
<profile type="contenttype">
    <title type="field">Жбистрой</title>
    <field_location type="field">
        <latitude>55.827247</latitude>
        <longitude>37.953821</longitude>
    </field_location>
    <taxonomy type="taxonomy">
        <term take_parents="0" vid="6">ЖБИ</term>
    </taxonomy>
    <field_goods type="field">
        <value></value>
    </field_goods>
    <field_address type="field">
        <value>Московская обл., Балашиха г., ул. Звездная, 7, корп.1</value>
    </field_address>
    <field_hours type="field">
         <value></value>
    </field_hours>
    <field_phone type="field">
        <value>+7 (495) 745-65-26</value>
    </field_phone>
    <field_email type="field">
        <value></value>
    </field_email>
</profile>
<profile type="contenttype">
    <title type="field">Компания КСК</title>
    <field_location type="field">
        <latitude>55.801050</latitude>
        <longitude>37.981695</longitude>
    </field_location>
    <taxonomy type="taxonomy">
        <term take_parents="0" vid="6">ЖБИ</term>
    </taxonomy>
    <field_goods type="field">
        <value></value>
    </field_goods>
    <field_address type="field">
        <value>Московская обл., Балашиха г., пл. Славы, 1</value>
    </field_address>
    <field_hours type="field">
         <value></value>
    </field_hours>
    <field_phone type="field">
        <value>+7 (495) 500-89-03</value>
    </field_phone>
    <field_phone type="field">
        <value>+7 (495) 720-51-36</value>
    </field_phone>
    <field_phone type="field">
        <value>+7 (495) 585-06-17</value>
    </field_phone>
    <field_phone type="field">
        <value>+7 (495) 545-56-17</value>
    </field_phone>
    <field_email type="field">
        <value></value>
    </field_email>
</profile>
<profile type="contenttype">
    <title type="field">Проект-М</title>
    <field_location type="field">
        <latitude>55.312548</latitude>
        <longitude>38.689460</longitude>
    </field_location>
    <taxonomy type="taxonomy">
        <term take_parents="0" vid="6">ЖБИ</term>
    </taxonomy>
    <field_goods type="field">
        <value></value>
    </field_goods>
    <field_address type="field">
        <value>Московская обл., Воскресенск г., ул. Заводская 2-я, 1</value>
    </field_address>
    <field_hours type="field">
         <value></value>
    </field_hours>
    <field_phone type="field">
        <value>+7 (495) 232-67-23</value>
    </field_phone>
    <field_email type="field">
        <value></value>
    </field_email>
</profile>
<profile type="contenttype">
    <title type="field">Стройкомбинат</title>
    <field_location type="field">
        <latitude>55.152747</latitude>
        <longitude>37.420446</longitude>
    </field_location>
    <taxonomy type="taxonomy">
        <term take_parents="0" vid="6">ЖБИ</term>
    </taxonomy>
    <field_goods type="field">
        <value></value>
    </field_goods>
    <field_address type="field">
        <value>Московская обл., Чеховский р-н, Чехов, ул. Угловая, Угловая ул., д. 2</value>
    </field_address>
    <field_hours type="field">
         <value></value>
    </field_hours>
    <field_phone type="field">
        <value>+7 (49672) 2-31-90</value>
    </field_phone>
    <field_email type="field">
        <value></value>
    </field_email>
</profile>
</items>